demos/__init__.py
demos/二维码登录.py
demos/云盘上传.py
demos/手机登录.py
demos/歌单同步.py
demos/获取单曲下载链接.py
demos/足迹伪装.py
pyncm/__init__.py
pyncm/__main__.py
pyncm/apis/__init__.py
pyncm/apis/album.py
pyncm/apis/artist.py
pyncm/apis/cloud.py
pyncm/apis/cloudsearch.py
pyncm/apis/exception.py
pyncm/apis/login.py
pyncm/apis/playlist.py
pyncm/apis/track.py
pyncm/apis/user.py
pyncm/apis/video.py
pyncm/apis/miniprograms/__init__.py
pyncm/apis/miniprograms/difm.py
pyncm/apis/miniprograms/radio.py
pyncm/apis/miniprograms/sportsfm.py
pyncm/apis/miniprograms/zonefm.py
pyncm/utils/__init__.py
pyncm/utils/aes.py
pyncm/utils/constant.py
pyncm/utils/crypto.py
pyncm/utils/helper.py
pyncm/utils/lrcparser.py
pyncm/utils/security.py
pyncm/utils/yrcparser.py
pyncm-1.8.1.dist-info/LICENSE
pyncm-1.8.1.dist-info/METADATA
pyncm-1.8.1.dist-info/WHEEL
pyncm-1.8.1.dist-info/entry_points.txt
pyncm-1.8.1.dist-info/top_level.txt
pyncm-1.8.1.dist-info/RECORD
