Metadata-Version: 2.1
Name: pyncm
Version: 1.8.1
Summary: NeteaseCloudMusic APIs for Python 3.x 适用于 Python 3 的网易云音乐 API
Home-page: https://github.com/greats3an/pyncm
Author: greats3an
Author-email: greats3an@gmail.com
Classifier: Programming Language :: Python :: 3
Classifier: License :: OSI Approved :: Apache Software License
Classifier: Operating System :: OS Independent
Requires-Python: >=3.6
License-File: LICENSE
Requires-Dist: requests
